baguette/__init__.py
baguette/api.py
baguette/config.py
baguette/errors.py
baguette/schema.py
baguette/utils.py
baguette/adapters/__init__.py
baguette/adapters/langchain.py
baguette/adapters/langgraph.py
baguette/adapters/sdk.py
baguette/audit/__init__.py
baguette/audit/injection.py
baguette/audit/journal.py
baguette/audit/traces.py
baguette/cli/__init__.py
baguette/cli/main.py
baguette/cli/storage.py
baguette/cli/utils.py
baguette/cli/commands/__init__.py
baguette/cli/commands/artifacts.py
baguette/cli/commands/config.py
baguette/cli/commands/journal.py
baguette/cli/commands/memory.py
baguette/cli/commands/replay.py
baguette/cli/commands/run.py
baguette/cli/commands/serve.py
baguette/cli/commands/trace.py
baguette/cli/commands/transactions.py
baguette/experimental/__init__.py
baguette/experimental/adapters/__init__.py
baguette/experimental/adapters/langgraph.py
baguette/experimental/adapters/memgpt.py
baguette/experimental/adapters/memu.py
baguette/experimental/adapters/reme.py
baguette/mcp/__init__.py
baguette/mcp/http.py
baguette/mcp/server.py
baguette/memory/__init__.py
baguette/memory/governance.py
baguette/memory/injection.py
baguette/memory/policy.py
baguette/memory/redaction.py
baguette/memory/transactions.py
baguette/memory/types.py
baguette/memory/validation.py
baguette/memory/verifiers.py
baguette/service/__init__.py
baguette/service/app.py
baguette/service/server.py
baguette/service/routes/__init__.py
baguette/service/routes/journal.py
baguette/service/routes/memory.py
baguette/service/routes/skills.py
baguette/service/routes/traces.py
baguette/service/routes/transactions.py
baguette/skills/__init__.py
baguette/skills/artifacts.py
baguette/skills/auto.py
baguette/skills/injection.py
baguette/skills/resolver.py
baguette/skills/runtime.py
baguette/skills/templating.py
baguette/skills/tool_adapters.py
baguette/skills/tools.py
baguette/skills/trace.py
baguette/storage/__init__.py
baguette/storage/base.py
baguette/storage/postgres.py
baguette_agent-0.1.0.dist-info/licenses/LICENSE
baguette_agent-0.1.0.dist-info/METADATA
baguette_agent-0.1.0.dist-info/WHEEL
baguette_agent-0.1.0.dist-info/entry_points.txt
baguette_agent-0.1.0.dist-info/top_level.txt
baguette_agent-0.1.0.dist-info/RECORD
