Metadata-Version: 2.4
Name: baguette-agent
Version: 0.1.0
Summary: Transactional memory + skill artifacts for AI agents
Author: HengYpinn
Requires-Python: >=3.10
License-File: LICENSE
Requires-Dist: PyYAML>=6.0
Requires-Dist: jinja2>=3.1
Requires-Dist: jsonschema>=4.21
Requires-Dist: semver>=3.0.0
Provides-Extra: langgraph
Requires-Dist: langgraph>=0.0.50; extra == "langgraph"
Provides-Extra: langchain
Requires-Dist: langchain>=0.1.0; extra == "langchain"
Provides-Extra: postgres
Requires-Dist: psycopg[binary]>=3.1; extra == "postgres"
Provides-Extra: service
Requires-Dist: fastapi>=0.110; extra == "service"
Requires-Dist: uvicorn>=0.24; extra == "service"
Dynamic: license-file
